{
  "BaseDataContract": null,
  "SearchAthenaListResponse": {
    "CollarId": null,
    "ComponentName": null,
    "ComponentVersionNo": null,
    "ConnectionString": null,
    "CurrentPage": 0,
    "DevicePhoneNo": null,
    "DistrictCode": null,
    "EndPoint": null,
    "ExternalURL": null,
    "FDSRequestString": null,
    "ForceCode": null,
    "Function": null,
    "GeoCoordinates": null,
    "IMEINo": null,
    "LayerName": null,
    "Location": null,
    "PNCDATA": null,
    "Process": null,
    "PropertyExt1": null,
    "PropertyExt2": null,
    "PropertyExt3": null,
    "PropertyExt4": null,
    "PropertyExt5": null,
    "ReasonCode": null,
    "Screen": null,
    "ScreenName": null,
    "SecurityContext": null,
    "Session": null,
    "SessionID": null,
    "StationCode": null,
    "SubProcess": null,
    "SubProcessName": null,
    "TotalPageCount": 0,
    "TotalRecordCount": 0,
    "TransactionId": null,
    "connectionStringIMAN": null,
    "addressList": null,
    "caseList": null,
    "communicationList": null,
    "courtWarrentList": [
      {
        "BCU": null,
        "BailedDate": null,
        "CCCJS": null,
        "Category": "A",
        "DOB": null,
        "DetailText": null,
        "Details": null,
        "District": null,
        "DueDate": "05/12/2021",
        "FlagDescription": "",
        "FlagMessage": "",
        "Force": null,
        "ForeName": null,
        "ID": "247008",
        "IssueDate": "10/12/2019",
        "OvertFlag": false,
        "SecureData": false,
        "Status": "ALLOCATED",
        "SubjectBailed": null,
        "SurName": "Surname: SKYWALKER<br/>Forename: Anakin<br/>DOB: 30/12/1952<br/>",
        "Type": "BREACH",
        "Ward": null,
        "Warnings": null,
        "WarrantNumber": null,
        "WarrantReference": "46/6/19",
        "logEntries": null,
        "relevantDateTime": null,
        "shortSummary": null
      }
    ],
    "investigationList": null,
    "personList": null,
    "vehicleList": null
  }
}