{
  "BaseDataContract": {
    "CollarId": null,
    "ComponentName": null,
    "ComponentVersionNo": null,
    "ConnectionString": null,
    "CurrentPage": 0,
    "DevicePhoneNo": null,
    "DistrictCode": null,
    "EndPoint": null,
    "ExternalURL": null,
    "FDSRequestString": "<FDSRequestString><FirstName>Peter </FirstName><LastName>Parker</LastName><DOB></DOB><ApproxAge></ApproxAge><PostCode></PostCode><ReasonCode>06-Administration</ReasonCode><VRM></VRM><Make></Make><Model></Model><Color></Color><HouseNo></HouseNo><Road></Road><City></City><County></County><Locality></Locality><UniqueID></UniqueID><TabName>NOMINAL</TabName><SearchType>NOMINAL</SearchType></FDSRequestString>",
    "ForceCode": null,
    "Function": null,
    "GeoCoordinates": null,
    "IMEINo": null,
    "LayerName": "DEVICE",
    "Location": null,
    "PNCDATA": null,
    "Process": "PNC",
    "PropertyExt1": null,
    "PropertyExt2": null,
    "PropertyExt3": "PNC",
    "PropertyExt4": null,
    "PropertyExt5": "<HistoryString><UniqueID>97/458591U</UniqueID><PNCID>97/458591U</PNCID><ReasonCode></ReasonCode><LastName>PARKER</LastName><FirstName> PETER</FirstName><Name>PARKER, PETER</Name><Ethnicity>WHITE NORTH EUROPEAN</Ethnicity><DLNo></DLNo><Height></Height><Warnings> </Warnings><DOB>29/10/82</DOB><CRONo></CRONo><FileName></FileName><PlaceOfBirth>HALIFAX</PlaceOfBirth><Gender>MALE</Gender><LastUpdatedDateTime>19/05/97 15:45</LastUpdatedDateTime><InformationMarker> </InformationMarker><MarksScars>PRCD  1</MarksScars><NominalAddress>29 SOUTH STREET  HALIFAX\r\nWEST YORKSHIRE    (13FA)\r\n</NominalAddress><WarningAlert></WarningAlert><LastAddressTypeandDate>(HOME) 19/05/97</LastAddressTypeandDate><SearchType>NOMINAL</SearchType></HistoryString>",
    "ReasonCode": "06-Administration",
    "Screen": null,
    "ScreenName": null,
    "SecurityContext": null,
    "Session": null,
    "SessionID": null,
    "StationCode": null,
    "SubProcess": "SEARCHNOMINALBYNAMEPNC",
    "SubProcessName": null,
    "TotalPageCount": 0,
    "TotalRecordCount": 0,
    "TransactionId": null,
    "connectionStringIMAN": null
  },
  "PersonByName": {
    "CurrentPage": "1",
    "PersonList": [
      {
        "AddressCount": "2",
        "Addresses": null,
        "AliasCount": "0",
        "AliasDOBCount": "0",
        "AliasNickNameCount": "0",
        "AliasNicknameDOB": null,
        "ArrestRemandCount": "0",
        "BailConditions": null,
        "BailConditionsCount": "0",
        "CRONo": null,
        "DLNo": null,
        "DNACount": "0",
        "DNAReport": null,
        "DOB": "29/10/82",
        "DescriptionCount": "2",
        "DisposableHistoryCount": "0",
        "DisposalHistory": null,
        "DisposalSummary": null,
        "DisposalSummaryCount": "1",
        "DisqualifiedDriverCount": "0",
        "DisqualifiedDriverReport": null,
        "Ethnicity": "WHITE NORTH EUROPEAN",
        "FileName": null,
        "FireArmCertificateCount": null,
        "FirstName": "PETER",
        "Gender": "MALE",
        "Height": null,
        "ImpendingProsecution": "0",
        "InformationMarker": " ",
        "InformationMarkerCount": null,
        "InternalCrossReferencesCount": null,
        "LastAddressTypeandDate": "(HOME) 19/05/97",
        "LastName": "PARKER",
        "LastUpdatedDateTime": "19/05/97 15:45",
        "LocalReferenceCount": null,
        "MarksAndScarsCount": null,
        "MarksScars": "PRCD  1",
        "Name": "PARKER, PETER",
        "NominalAddress": "29 SOUTH STREET  HALIFAX\r\nWEST YORKSHIRE    (13FA)\r\n",
        "OperationalInfoCount": "0",
        "OtherInformation": "(HOME) 19/05/97",
        "PNCID": "97/458591U",
        "PhotoLocationCount": "0",
        "PhotoLocationGroup": null,
        "PlaceofBirth": "HALIFAX",
        "SequenceNo": null,
        "Type": null,
        "WantedMissing": null,
        "WantedandMissingCount": "1",
        "WarningAlert": null,
        "WarningandAlertCount": null,
        "Warnings": " "
      }
    ],
    "TotalPageCount": "1",
    "TotalRecordCount": "3",
    "TotalRecordCountString": "3 POSSIBLES"
  }
}